setup.py
file_deleter/__init__.py
file_deleter.egg-info/PKG-INFO
file_deleter.egg-info/SOURCES.txt
file_deleter.egg-info/dependency_links.txt
file_deleter.egg-info/not-zip-safe
file_deleter.egg-info/top_level.txt