Metadata-Version: 1.0
Name: file-deleter
Version: 0.0.1
Summary: Delete all files that match pattern and was created before timepoint.
Home-page: UNKNOWN
Author: Dmitry Shevelev
Author-email: estranium@gmail.com
License: MIT
Platform: UNKNOWN
